{
    "直接播放": "1",
    "站名": "啊哈DJ网",
    "分类url": "https://m.ahadj.com/music/{cateId}-{catePg}.html;;a",
    "分类": "华语超清MV$id-31#国外超清MV$id-44#车载音乐$id-85#中文DJ单曲$id-22#粤语DJ舞曲$id-29#草原DJ舞曲$id-35#经典粤语歌曲$id-54#中文DJ串烧$id-63#优美纯音乐$id-120#欧美单曲$id-13#国外串烧$id-6#蓝调爵士$id-117#club 舞曲$id-110#说唱歌曲$id-53#印度舞曲$id-47#Vocal House$id-43#Pure House$id-42#Club Dance$id-40#FunkyHouse$id-39#Mash Up$id-38#ElectroHouse$id-37#DutchHouse$id-36#英文歌曲$id-30#Club House$id-41#纯DJ音乐$id-121#Crooklyn$id-140#Dubstep$id-141#Tits Exclu$id-143#Chartbusters$id-144#Bounce EDM$id-146#Beezo BeeHive$id-147#Tech House$id-148#Headliner$id-149#Nothing$id-150#Rock$id-151#Techno$id-152#Transition$id-153#原味越鼓$id-184#Ibiza 舞曲$id-135#BigRoom$id-134#MyMP3Pool$id-133#Trap 舞曲$id-132#BarBangerz$id-131#Club Killers$id-130#House Dance$id-129#HouseFuture$id-128#Deep House$id-127#Deep 舞曲$id-126#Exclusive$id-124#Hip Hop$id-119#雷鬼音乐$id-118#无损中文舞曲$id-16#无损英文舞曲$id-17#无损中文歌曲$id-18#无损英文歌曲$id-19#无损串烧舞曲$id-33#车载3D音乐$id-116#外文3D舞曲$id-92#中文3D舞曲$id-93#8倍音质草原歌$id-137#8倍音质国外曲$id-138#8倍音质歌曲$id-164#中文抖音歌曲$id-168#英文抖音音乐$id-169#并四$id-67#自由步$id-82#广场舞曲$id-81#三步踩$id-80#拉丁$id-79#桑巴$id-78#摇并$id-77#吉特巴$id-76#探戈$id-75#恰恰$id-74#伦巴$id-73#慢三$id-72#中三$id-71#快三$id-70#慢四$id-69#快四$id-68#中四$id-66#华尔兹$id-139#中文的士高$id-166#国外的士高$id-167#DJ伴奏$id-165",
    "起始页": "1",
    "数组二次截取": "yinyue yinyue2 mt20\">&&</div>",
    "数组": "<li&&<dl class=\"clearfix",
    "标题": "<h3>&&</h3>",
    "图片": "src=\"&&\"",
    "链接": "href=\"&&\""
}